jscaffold/__init__.py
jscaffold/_version.py
jscaffold/debounce.py
jscaffold/form.py
jscaffold/processor.py
jscaffold/utils.py
jscaffold/contexts/context.py
jscaffold/decorators/iot.py
jscaffold/iounit/__init__.py
jscaffold/iounit/applytosource.py
jscaffold/iounit/blockinfilevar.py
jscaffold/iounit/envfilevar.py
jscaffold/iounit/envvar.py
jscaffold/iounit/format.py
jscaffold/iounit/iounit.py
jscaffold/iounit/jsonfilevar.py
jscaffold/iounit/valuable.py
jscaffold/iounit/var.py
jscaffold/panel/__init__.py
jscaffold/panel/formpanel.py
jscaffold/panel/mainpanel.py
jscaffold/patchers/assign.py
jscaffold/patchers/block.py
jscaffold/patchers/dict.py
jscaffold/services/changedispatcher.py
jscaffold/services/sharedstorage.py
jscaffold/services/tkservice.py
jscaffold/task/runtask.py
jscaffold/tests/__init__.py
jscaffold/tests/conftest.py
jscaffold/tests/test_applytosource.py
jscaffold/tests/test_blockinfilevar.py
jscaffold/tests/test_changedispatcher.py
jscaffold/tests/test_debounce.py
jscaffold/tests/test_decorators_iot.py
jscaffold/tests/test_envfilevar.py
jscaffold/tests/test_envvar.py
jscaffold/tests/test_form.py
jscaffold/tests/test_formatable.py
jscaffold/tests/test_formpanel.py
jscaffold/tests/test_inputwidget.py
jscaffold/tests/test_jsonfilevar.py
jscaffold/tests/test_patchers_assign.py
jscaffold/tests/test_patchers_dict.py
jscaffold/tests/test_processor.py
jscaffold/tests/test_runtask.py
jscaffold/tests/test_scaffoldvar.py
jscaffold/tests/test_utils.py
jscaffold/tests/test_valuable.py
jscaffold/tests/test_widgetfactory.py
jscaffold/tests/patchers/test_patchers_block.py
jscaffold/views/logger.py
jscaffold/views/logview/index.js
jscaffold/views/logview/logview.py
jscaffold/views/logview/style.css
jscaffold/widgets/columnflow.py
jscaffold/widgets/inputwidget.py
jscaffold/widgets/ipywidgetwrapper.py
jscaffold/widgets/widgetfactory.py
jscaffold-0.0.1.dist-info/LICENSE
jscaffold-0.0.1.dist-info/METADATA
jscaffold-0.0.1.dist-info/WHEEL
jscaffold-0.0.1.dist-info/top_level.txt
jscaffold-0.0.1.dist-info/RECORD
