Metadata-Version: 2.1
Name: jscaffold
Version: 0.0.1
Summary: Jupyter Scaffold
Home-page: https://github.com/benlau/jscaffold
Author: Ben lau
Author-email: xbenlau@gmail.com
License: BSD
Keywords: Jupyter,Widgets,IPython
Platform: Linux
Platform: Mac OS X
Platform: Windows
Classifier: Intended Audience :: Developers
Classifier: Intended Audience :: Science/Research
Classifier: License :: OSI Approved :: BSD License
Classifier: Programming Language :: Python
Classifier: Programming Language :: Python :: 3
Classifier: Programming Language :: Python :: 3.4
Classifier: Programming Language :: Python :: 3.5
Classifier: Programming Language :: Python :: 3.6
Classifier: Programming Language :: Python :: 3.7
Classifier: Framework :: Jupyter
Requires-Python: >=3.6
License-File: LICENSE
Requires-Dist: ipywidgets>=7.0.0
Requires-Dist: anywidget>=0.9.6
Provides-Extra: docs
Provides-Extra: examples
Provides-Extra: test
Requires-Dist: pytest>=4.6; extra == "test"
Requires-Dist: pytest-cov; extra == "test"
Requires-Dist: nbval; extra == "test"
